arty_random_test_lib/__init__.py
arty_random_test_lib/hello_world.py
arty_random_test_lib-1.0.0.dist-info/LICENSE
arty_random_test_lib-1.0.0.dist-info/METADATA
arty_random_test_lib-1.0.0.dist-info/WHEEL
arty_random_test_lib-1.0.0.dist-info/top_level.txt
arty_random_test_lib-1.0.0.dist-info/RECORD
