Metadata-Version: 2.1
Name: arty-random-test-lib
Version: 1.0.0
Summary: Dummy utility library
Home-page: https://github.com/kenshinapa/GenericPythonLib.git
Author: Arturo Padilla Ayala
Author-email: r2padillaayala@gmail.com
License-File: LICENSE
Requires-Dist: Cerberus (>=1.3.4)
